{
  "smsFormat": [
    {
      "id": 1,
      "sender": "TM-CITIBA",
      "type": "debit",
      "regex_Format": "(?i)Your [[account]] A\\/c has been debited with INR [[amount]] on [[date]] at [[time]] and account [[to]](?<= has) been credited..*"
    },
    {
      "id": 2,
      "sender": "TM-CITIBA",
      "type": "credit",
      "regex_Format": "(?i)Your [[account]] A\/c has been credited with INR [[amount]] on [[date]] at [[time]] received from [[to]]..*"
    },
    {
      "id": 3,
      "sender": "JM-ICICIB",
      "type": "debit",
      "regex_Format": "(?i)INR [[amount]] spent on ICICI Bank Card [[account]] on [[date]] at [[to]]..*"
    },
    {
      "id": 4,
      "sender": "JM-ICICIB",
      "type": "debit",
      "regex_Format": "(?i)Dear Customer, ICICI Bank Account [[account]] is debited with INR [[amount]] on [[date]]. Info: [[to]]..*"
    },
    {
      "id": 5,
      "sender": "JM-ICICIB",
      "type": "debit",
      "regex_Format": "(?i)ICICI Bank Acct [[account]] debited for Rs [[amount]] on [[date]]; [[to]](?<= credited)..*"
    },
    {
      "id": 6,
      "sender": "AD-ICICIB",
      "type": "debit",
      "regex_Format": "(?i)ICICI Bank Acct [[account]] debited for Rs [[amount]] on [[date]]; [[to]](?<= credited)..*"
    },
    {
      "id": 7,
      "sender": "JM-CITIBA",
      "type": "credit",
      "regex_Format": "(?i)Rs.[[amount]] is credited to your a\/c [[account]] from Citi Account of [[to]](?<= on) [[date]] [[time]] \\(Ref no..*"
    }
  ]
}